LICENSE.txt
MANIFEST.in
README.rst
setup.py
checkfort/__init__.py
checkfort/exceptions.py
checkfort/filegen.py
checkfort/files.py
checkfort/forcheck.py
checkfort/launcher.py
checkfort/lexer.py
checkfort/logging.py
checkfort/parser.py
checkfort.egg-info/PKG-INFO
checkfort.egg-info/SOURCES.txt
checkfort.egg-info/dependency_links.txt
checkfort.egg-info/entry_points.txt
checkfort.egg-info/requires.txt
checkfort.egg-info/top_level.txt
checkfort/templates/base.html
checkfort/templates/code_source.html
checkfort/templates/event.html
checkfort/templates/index.html
checkfort/templates/style.css