Metadata-Version: 1.1
Name: checkfort
Version: 0.1.0
Summary: A wrapper tool for FORCHECK.
Home-page: https://github.com/shawnchin/checkfort
Author: Shawn Chin
Author-email: shawn.chin@stfc.ac.uk
License: BSD
Keywords: fortran forcheck static_analysis software_tools
Platform: UNKNOWN
Classifier: Development Status :: 3 - Alpha
Classifier: Environment :: Console
Classifier: Intended Audience :: Developers
Classifier: License :: OSI Approved :: BSD License
Classifier: Operating System :: POSIX :: Linux
Classifier: Programming Language :: Python :: 2.6
Classifier: Programming Language :: Python :: 2.7
Classifier: Topic :: Software Development :: Quality Assurance
Classifier: Topic :: Utilities
